LICENSE
MANIFEST.in
README.rst
setup.py
skilltree/__init__.py
skilltree/points.txt
skilltree/skills.txt
skilltree.egg-info/PKG-INFO
skilltree.egg-info/SOURCES.txt
skilltree.egg-info/dependency_links.txt
skilltree.egg-info/requires.txt
skilltree.egg-info/top_level.txt
skilltree/img/L0.png
skilltree/img/L1.png
skilltree/img/L2.png
skilltree/img/L3.png
skilltree/img/L4.png
skilltree/img/L5.png