Metadata-Version: 2.1
Name: skilltree
Version: 1.0.10
Summary: skills for material physics
Home-page: UNKNOWN
Author: BrienZhang
Author-email: brienzhang@sina.com
Maintainer: Brien
Maintainer-email: 
License: MIT
Platform: all
Classifier: Intended Audience :: Developers
Classifier: Operating System :: OS Independent
Classifier: Natural Language :: Chinese (Simplified)
Classifier: Programming Language :: Python
Classifier: Programming Language :: Python :: 3.5
Classifier: Programming Language :: Python :: 3.6
Classifier: Programming Language :: Python :: 3.7
Classifier: Programming Language :: Python :: 3.8
Classifier: Topic :: Software Development :: Libraries
License-File: LICENSE
